fastapi_auth0/__init__.py
fastapi_auth0/auth.py
fastapi_auth0/py.typed
fastapi_auth0_pyjwt-0.6.3.dist-info/licenses/LICENSE.txt
fastapi_auth0_pyjwt-0.6.3.dist-info/METADATA
fastapi_auth0_pyjwt-0.6.3.dist-info/WHEEL
fastapi_auth0_pyjwt-0.6.3.dist-info/top_level.txt
fastapi_auth0_pyjwt-0.6.3.dist-info/RECORD
