Metadata-Version: 2.4
Name: fastapi-auth0-pyjwt
Version: 0.6.3
Summary: Easy auth0.com integration for FastAPI and PyJWT
Home-page: https://github.com/spawn-guy/fastapi-auth0
Author: Dorin Clisu
Maintainer: Paul Rysiavets
License: MIT
Requires-Python: >=3.7
License-File: LICENSE.txt
Requires-Dist: fastapi>=0.60.0
Requires-Dist: PyJWT>=2.8.0
Dynamic: author
Dynamic: description
Dynamic: description-content-type
Dynamic: home-page
Dynamic: license
Dynamic: license-file
Dynamic: maintainer
Dynamic: requires-dist
Dynamic: requires-python
Dynamic: summary
